chemcalculator/__init__.py
chemcalculator/chemcalculator.py
chemcalculator/data/Periodic-Table-of-Elements.csv
chemcalculator/data/__init__.py
chemcalculator/datasets.py
chemcalculator/helper.py
chemcalculator-0.1.12.dist-info/LICENSE
chemcalculator-0.1.12.dist-info/WHEEL
chemcalculator-0.1.12.dist-info/METADATA
chemcalculator-0.1.12.dist-info/RECORD
