Metadata-Version: 2.1
Name: chemcalculator
Version: 0.1.12
Summary: Calculate chemical formula mass or atomic mass (g/mol), convert moles to grams and grams to moles, and calculate percentage mass for chemical or atom of interest
Home-page: https://github.com/UBC-MDS/chemcalculator
License: MIT
Author: Joyce Wang, Kinslin Lv, Allyson Stoll
Requires-Python: >=3.9,<4.0
Classifier: License :: OSI Approved :: MIT License
Classifier: Programming Language :: Python :: 3
Classifier: Programming Language :: Python :: 3.10
Classifier: Programming Language :: Python :: 3.9
Requires-Dist: pandas (>=1.4.0,<2.0.0)
Project-URL: Documentation, https://chemcalculator.readthedocs.io/
Project-URL: Repository, https://github.com/UBC-MDS/chemcalculator
